ion_networks/__init__.py
ion_networks/_version.py
ion_networks/browser.py
ion_networks/interface.py
ion_networks/ion_networks.py
ion_networks/ms_database.py
ion_networks/ms_run_files.py
ion_networks/ms_utils.py
ion_networks/numba_functions.py
ion_networks/sandbox.py
ion_networks/sandbox_browser.py
ion_networks/sandbox_browser2.py
ion_networks/sandbox_lfq_calculations.py
ion_networks/lib/browser_images/load_animation.gif
ion_networks/lib/browser_images/network.png
ion_networks/lib/browser_images/nodes.png
ion_networks/lib/browser_images/pointer.png
ion_networks/lib/browser_images/pointer_25x25.png
ion_networks/lib/browser_images/pointer_30x30.png
ion_networks/lib/default_parameters/annotation_parameters.json
ion_networks/lib/default_parameters/convert_parameters.json
ion_networks/lib/default_parameters/create_parameters.json
ion_networks/lib/default_parameters/database_parameters.json
ion_networks/lib/default_parameters/evidence_parameters.json
ion_networks/lib/default_parameters/interface_parameters.json
ion_networks/lib/default_parameters/mgf_parameters.json
Ion_networks-2.0.200821.dist-info/LICENSE.txt
Ion_networks-2.0.200821.dist-info/METADATA
Ion_networks-2.0.200821.dist-info/WHEEL
Ion_networks-2.0.200821.dist-info/entry_points.txt
Ion_networks-2.0.200821.dist-info/top_level.txt
Ion_networks-2.0.200821.dist-info/RECORD
