Metadata-Version: 2.1
Name: Ion-networks
Version: 2.0.200821
Summary: Analysis of LC-[...]-MSMS data with ion-networks
Home-page: https://github.com/swillems/ion_networks
Author: Sander Willems
Author-email: sander.willems@ugent.be
License: MIT
Project-URL: Publication, https://www.biorxiv.org/content/10.1101/726273v2
Keywords: MS,Mass spectrometry,Proteomics,DIA,Data-independent acquisition
Platform: UNKNOWN
Classifier: Development Status :: 3 - Alpha
Classifier: License :: OSI Approved :: MIT License
Classifier: Intended Audience :: Science/Research
Classifier: Operating System :: POSIX :: Linux
Classifier: Programming Language :: Python :: 3
Classifier: Programming Language :: Python :: 3.6
Classifier: Programming Language :: Python :: 3 :: Only
Classifier: Topic :: Scientific/Engineering :: Bio-Informatics
Requires-Python: >=3.6,<4
Requires-Dist: numpy
Requires-Dist: numexpr
Requires-Dist: matplotlib (==3.2.2)
Requires-Dist: PySimpleGUI
Requires-Dist: pandas
Requires-Dist: click
Requires-Dist: scipy
Requires-Dist: scikit-learn
Requires-Dist: h5py
Requires-Dist: pyteomics
Requires-Dist: numba
Requires-Dist: pyqt5-sip
Requires-Dist: pyqtwebengine
Provides-Extra: ms2pip
Requires-Dist: ms2pip ; extra == 'ms2pip'
